entity/__init__.py
entity/entity.py
entity_extract-0.0.1.dist-info/DESCRIPTION.rst
entity_extract-0.0.1.dist-info/METADATA
entity_extract-0.0.1.dist-info/RECORD
entity_extract-0.0.1.dist-info/WHEEL
entity_extract-0.0.1.dist-info/metadata.json
entity_extract-0.0.1.dist-info/top_level.txt
